[
    {
        "path": "/assets/js/jquery.min.js",
        "type": "js",
        "position": "header",
        "base": "template"
    },
    {
        "path": "/assets/js/jquery-noconflict.js",
        "type": "js",
        "position": "header",
        "base": "template"
    },
    {
        "path": "/assets/js/ekko-lightbox.js",
        "type": "js",
        "position": "footer",
        "base": "template"
    },
    {
        "path": "/assets/css/normalize.css",
        "type": "css",
        "options": {
            "rel": "stylesheet"
        },
        "position": "header",
        "base": "template"
    },
    {
        "path": "/assets/js/megamenu.js",
        "type": "js",
        "position": "footer",
        "base": "template"
    },
    {
        "path": "/assets/less/template.less",
        "type": "less",
        "options": {
            "rel": "stylesheet"
        },
        "position": "header",
        "base": "template"
    }
]

